{
  "8086:0102": {"name": "Intel HD Graphics 2000", "vram_mb": 512},
  "8086:0112": {"name": "Intel HD Graphics 3000", "vram_mb": 384},
  "8086:0116": {"name": "Intel HD Graphics 3000", "vram_mb": 384},
  "8086:0126": {"name": "Intel HD Graphics 3000", "vram_mb": 512},
  "8086:0152": {"name": "Intel HD Graphics 2500", "vram_mb": 1024},
  "8086:0156": {"name": "Intel HD Graphics 2500", "vram_mb": 1024},
  "8086:0162": {"name": "Intel HD Graphics 4000", "vram_mb": 1024},
  "8086:0166": {"name": "Intel HD Graphics 4000", "vram_mb": 1024},
  "8086:016a": {"name": "Intel HD Graphics P4000", "vram_mb": 1024},
  "8086:0402": {"name": "Intel HD Graphics", "vram_mb": 1024},
  "8086:0412": {"name": "Intel HD Graphics 4600", "vram_mb": 1024},
  "8086:0416": {"name": "Intel HD Graphics 4600", "vram_mb": 1024},
  "8086:041a": {"name": "Intel HD Graphics P4600", "vram_mb": 1024},
  "8086:041e": {"name": "Intel HD Graphics 4400", "vram_mb": 1024},
  "8086:0a06": {"name": "Intel HD Graphics", "vram_mb": 1024},
  "8086:0a16": {"name": "Intel HD Graphics 4400", "vram_mb": 1024},
  "8086:0a1e": {"name": "Intel HD Graphics 4200", "vram_mb": 1024},
  "8086:0a26": {"name": "Intel HD Graphics 5000", "vram_mb": 1536},
  "8086:0a2e": {"name": "Intel Iris Graphics 5100", "vram_mb": 1536},
  "8086:0d22": {"name": "Intel Iris Pro Graphics 5200", "vram_mb": 1536},
  "8086:0d26": {"name": "Intel Iris Pro Graphics 5200", "vram_mb": 1536},
  "8086:1606": {"name": "Intel HD Graphics", "vram_mb": 1536},
  "8086:1612": {"name": "Intel HD Graphics 5600", "vram_mb": 1536},
  "8086:1616": {"name": "Intel HD Graphics 5500", "vram_mb": 1536},
  "8086:161e": {"name": "Intel HD Graphics 5300", "vram_mb": 1536},
  "8086:1622": {"name": "Intel Iris Pro Graphics 6200", "vram_mb": 1536},
  "8086:1626": {"name": "Intel HD Graphics 6000", "vram_mb": 1536},
  "8086:162b": {"name": "Intel Iris Graphics 6100", "vram_mb": 1536},
  "8086:1902": {"name": "Intel HD Graphics 510", "vram_mb": 1536},
  "8086:1906": {"name": "Intel HD Graphics 510", "vram_mb": 1536},
  "8086:1912": {"name": "Intel HD Graphics 530", "vram_mb": 1536},
  "8086:1916": {"name": "Intel HD Graphics 520", "vram_mb": 1536},
  "8086:191b": {"name": "Intel HD Graphics 530", "vram_mb": 1536},
  "8086:191e": {"name": "Intel HD Graphics 515", "vram_mb": 1536},
  "8086:1926": {"name": "Intel Iris Graphics 540", "vram_mb": 1536},
  "8086:1927": {"name": "Intel Iris Graphics 550", "vram_mb": 1536},
  "8086:193b": {"name": "Intel Iris Pro Graphics 580", "vram_mb": 1536},
  "8086:5902": {"name": "Intel HD Graphics 610", "vram_mb": 1536},
  "8086:5906": {"name": "Intel HD Graphics 610", "vram_mb": 1536},
  "8086:5912": {"name": "Intel HD Graphics 630", "vram_mb": 1536},
  "8086:5916": {"name": "Intel HD Graphics 620", "vram_mb": 1536},
  "8086:5917": {"name": "Intel UHD Graphics 620", "vram_mb": 1536},
  "8086:591b": {"name": "Intel HD Graphics 630", "vram_mb": 1536},
  "8086:591e": {"name": "Intel HD Graphics 615", "vram_mb": 1536},
  "8086:5926": {"name": "Intel Iris Plus Graphics 640", "vram_mb": 1536},
  "8086:5927": {"name": "Intel Iris Plus Graphics 650", "vram_mb": 1536},
  "8086:3e90": {"name": "Intel UHD Graphics 610", "vram_mb": 1536},
  "8086:3e91": {"name": "Intel UHD Graphics 630", "vram_mb": 1536},
  "8086:3e92": {"name": "Intel UHD Graphics 630", "vram_mb": 1536},
  "8086:3e98": {"name": "Intel UHD Graphics 630", "vram_mb": 1536},
  "8086:3e9b": {"name": "Intel UHD Graphics 630", "vram_mb": 1536},
  "8086:3ea0": {"name": "Intel UHD Graphics 620", "vram_mb": 1536},
  "8086:3ea5": {"name": "Intel Iris Plus Graphics 655", "vram_mb": 1536},
  "10de:1c8c": {"name": "NVIDIA GeForce GTX 1050 Ti", "vram_mb": 4096},
  "10de:1c8d": {"name": "NVIDIA GeForce GTX 1050", "vram_mb": 2048},
  "10de:1c20": {"name": "NVIDIA GeForce GTX 1060", "vram_mb": 6144},
  "10de:1b80": {"name": "NVIDIA GeForce GTX 1080", "vram_mb": 8192},
  "10de:1b81": {"name": "NVIDIA GeForce GTX 1070", "vram_mb": 8192},
  "1002:67df": {"name": "AMD Radeon RX 580", "vram_mb": 8192},
  "1002:699f": {"name": "AMD Radeon RX 550", "vram_mb": 4096},
  "1002:6938": {"name": "AMD Radeon R9 M395X", "vram_mb": 4096},
  "1002:687f": {"name": "Radeon Pro Vega 56", "vram_mb": 8192},
  "1002:6860": {"name": "Radeon Pro Vega 64", "vram_mb": 16384},
  "1002:6861": {"name": "Radeon Pro Vega 56", "vram_mb": 8192}
}
